setup.py
distributions_gordon_test/Binomialdistribution.py
distributions_gordon_test/Gaussiandistribution.py
distributions_gordon_test/Generaldistribution.py
distributions_gordon_test/__init__.py
distributions_gordon_test.egg-info/PKG-INFO
distributions_gordon_test.egg-info/SOURCES.txt
distributions_gordon_test.egg-info/dependency_links.txt
distributions_gordon_test.egg-info/not-zip-safe
distributions_gordon_test.egg-info/top_level.txt